scintipulses/__init__.py
scintipulses/scintiPulses.py
scintipulses/test_scintiPulses.py
scintipulses-2.2.dist-info/licenses/LICENCE.md
scintipulses-2.2.dist-info/METADATA
scintipulses-2.2.dist-info/WHEEL
scintipulses-2.2.dist-info/top_level.txt
scintipulses-2.2.dist-info/RECORD
